NcpSemApi/__init__.py
NcpSemApi/apiauth.py
NcpSemApi/azure.py
NcpSemApi/base.py
NcpSemApi/cached_property.py
NcpSemApi/client.py
NcpSemApi/firewall.py
NcpSemApi/group.py
NcpSemApi/ldap.py
NcpSemApi/license.py
NcpSemApi/okta_api.py
NcpSemApi/pki.py
NcpSemApi/radius.py
NcpSemApi/sem.py
NcpSemApi/semmgm.py
NcpSemApi/srvmgm.py
NcpSemApi/traceloggers.py
NcpSemApi/ui.py
NcpSemApi/version.py
NcpSemApi-1.3.31900.dist-info/METADATA
NcpSemApi-1.3.31900.dist-info/WHEEL
NcpSemApi-1.3.31900.dist-info/top_level.txt
NcpSemApi-1.3.31900.dist-info/RECORD
