Metadata-Version: 2.1
Name: NcpSemApi
Version: 1.3.31900
Summary: Python API of the NCP secure enterprise management server
Home-page: https://ncp-e.com
Author: NCP engineering GmbH
Author-email: info@ncp-e.com
License: Proprietary
Classifier: Programming Language :: Python :: 3
Classifier: License :: Other/Proprietary License
Classifier: Operating System :: OS Independent
Requires-Python: >=3.9
Provides-Extra: azure-support
Requires-Dist: msal ; extra == 'azure-support'
Requires-Dist: requests ; extra == 'azure-support'
Provides-Extra: ldap-support
Requires-Dist: ldap3 ; extra == 'ldap-support'
Provides-Extra: okta-support
Requires-Dist: okta ; extra == 'okta-support'
